serviceform/serviceform/__init__.py
serviceform/serviceform/admin.py
serviceform/serviceform/apps.py
serviceform/serviceform/emails.py
serviceform/serviceform/forms.py
serviceform/serviceform/tasks.py
serviceform/serviceform/urls.py
serviceform/serviceform/utils.py
serviceform/serviceform/locale/en/LC_MESSAGES/django.mo
serviceform/serviceform/locale/fi/LC_MESSAGES/django.mo
serviceform/serviceform/management/__init__.py
serviceform/serviceform/management/commands/__init__.py
serviceform/serviceform/management/commands/create_default_email_templates.py
serviceform/serviceform/management/commands/send_emails.py
serviceform/serviceform/migrations/0001_initial.py
serviceform/serviceform/migrations/__init__.py
serviceform/serviceform/models/__init__.py
serviceform/serviceform/models/email.py
serviceform/serviceform/models/mixins.py
serviceform/serviceform/models/participation.py
serviceform/serviceform/models/people.py
serviceform/serviceform/models/serviceform.py
serviceform/serviceform/static/__init__.py
serviceform/serviceform/static/admin.js
serviceform/serviceform/static/awesome-bootstrap-checkbox.scss
serviceform/serviceform/static/jquery.are-you-sure.js
serviceform/serviceform/static/Font-Awesome/__init__.py
serviceform/serviceform/static/Font-Awesome/fonts/FontAwesome.otf
serviceform/serviceform/static/Font-Awesome/fonts/__init__.py
serviceform/serviceform/static/Font-Awesome/fonts/fontawesome-webfont.eot
serviceform/serviceform/static/Font-Awesome/fonts/fontawesome-webfont.svg
serviceform/serviceform/static/Font-Awesome/fonts/fontawesome-webfont.ttf
serviceform/serviceform/static/Font-Awesome/fonts/fontawesome-webfont.woff
serviceform/serviceform/static/Font-Awesome/fonts/fontawesome-webfont.woff2
serviceform/serviceform/static/Font-Awesome/scss/__init__.py
serviceform/serviceform/static/Font-Awesome/scss/_animated.scss
serviceform/serviceform/static/Font-Awesome/scss/_bordered-pulled.scss
serviceform-0.9.8.dist-info/DESCRIPTION.rst
serviceform-0.9.8.dist-info/METADATA
serviceform-0.9.8.dist-info/RECORD
serviceform-0.9.8.dist-info/WHEEL
serviceform-0.9.8.dist-info/metadata.json
serviceform-0.9.8.dist-info/top_level.txt
