Metadata-Version: 2.0
Name: serviceform
Version: 0.9.8
Summary: Django web application to collect volunteering willingness data and report to responsible people
Home-page: https://github.com/tuomas2/serviceform
Author: Tuomas Airaksinen
Author-email: tuomas.airaksinen@gmail.com
License: GPL
Keywords: django,church,volunteering,recruiting,reporting
Platform: UNKNOWN
Classifier: Natural Language :: English
Classifier: Natural Language :: Finnish
Classifier: Framework :: Django
Classifier: Intended Audience :: Religion
Classifier: Intended Audience :: Education
Classifier: License :: OSI Approved :: GNU General Public License v3 (GPLv3)
Classifier: Environment :: Web Environment
Classifier: Programming Language :: Python :: 3
Classifier: Programming Language :: Python :: 3.6
Classifier: Programming Language :: Python :: 3 :: Only
Requires-Dist: Django
Requires-Dist: colour
Requires-Dist: django-colorful
Requires-Dist: django-compressor
Requires-Dist: django-crispy-forms
Requires-Dist: django-guardian
Requires-Dist: django-libsass
Requires-Dist: django-nested-admin
Requires-Dist: django-redis-cache
Requires-Dist: django-select2-forms
Requires-Dist: psycopg2
Requires-Dist: raven
Provides-Extra: cachalot
Requires-Dist: django-cachalot; extra == 'cachalot'
Provides-Extra: celery
Requires-Dist: celery; extra == 'celery'
Requires-Dist: django-celery; extra == 'celery'
Provides-Extra: grappelli
Requires-Dist: django-grappelli; extra == 'grappelli'
